Workbook

Sheet DRE 2025
A1: Vida Plena S.A. — Demonstração do Resultado do Exercício
A2: Relatório Financeiro Consolidado | Exercício de 2025 (Valores em R$)
A4: Conta DRE | B4: Valor (R$) | C4: % da Receita Bruta
A5: Receita Bruta | B5: 48500000 | C5: =B5/$B$5
A6: Deduções da Receita (Impostos sobre Vendas / Devoluções) | B6: -4365000 | C6: =B6/$B$5
A7: Receita Líquida | B7: =B5+B6 | C7: =B7/$B$5
A8: Custos Operacionais (COGS / Licenciamento / Cloud) | B8: -17654000 | C8: =B8/$B$5
A9: Lucro Bruto | B9: =B7+B8 | C9: =B9/$B$5
A10: Despesas Administrativas | B10: -5320000 | C10: =B10/$B$5
A11: Despesas Comerciais & Marketing | B11: -6180000 | C11: =B11/$B$5
A12: Despesas Financeiras Líquidas | B12: -980000 | C12: =B12/$B$5
A13: Resultado Operacional (EBIT) | B13: =B9+SUM(B10:B12) | C13: =B13/$B$5
A14: Impostos (IRPJ e CSLL) | B14: -2797530 | C14: =B14/$B$5
A15: Lucro Líquido do Exercício | B15: =B13+B14 | C15: =B15/$B$5

Sheet Comparativo Mensal
A1: Vida Plena S.A. — Evolução Mensal do Resultado (2025)
A2: Detalhamento Mensal de Receita, Custos, Despesas e Lucros (em R$)
A4: Mês | B4: Receita Líquida | C4: Custos Operacionais | D4: Despesas Operacionais | E4: Lucro Operacional | F4: Lucro Líquido
A5: Janeiro | B5: 3450000 | C5: 1380000 | D5: 980000 | E5: =B5-C5-D5 | F5: =E5*0.79
A6: Fevereiro | B6: 3520000 | C6: 1408000 | D6: 990000 | E6: =B6-C6-D6 | F6: =E6*0.79
A7: Março | B7: 3680000 | C7: 1472000 | D7: 1010000 | E7: =B7-C7-D7 | F7: =E7*0.79
A8: Abril | B8: 3600000 | C8: 1440000 | D8: 1000000 | E8: =B8-C8-D8 | F8: =E8*0.79
A9: Maio | B9: 3750000 | C9: 1500000 | D9: 1020000 | E9: =B9-C9-D9 | F9: =E9*0.79
A10: Junho | B10: 3820000 | C10: 1528000 | D10: 1030000 | E10: =B10-C10-D10 | F10: =E10*0.79
A11: Julho | B11: 3900000 | C11: 1560000 | D11: 1040000 | E11: =B11-C11-D11 | F11: =E11*0.79
A12: Agosto | B12: 3850000 | C12: 1540000 | D12: 1035000 | E12: =B12-C12-D12 | F12: =E12*0.79
A13: Setembro | B13: 4020000 | C13: 1608000 | D13: 1060000 | E13: =B13-C13-D13 | F13: =E13*0.79
A14: Outubro | B14: 4100000 | C14: 1640000 | D14: 1070000 | E14: =B14-C14-D14 | F14: =E14*0.79
A15: Novembro | B15: 4180000 | C15: 1672000 | D15: 1080000 | E15: =B15-C15-D15 | F15: =E15*0.79
A16: Dezembro | B16: 4265000 | C16: 1706000 | D16: 1090000 | E16: =B16-C16-D16 | F16: =E16*0.79
A17: Total Acumulado | B17: =SUM(B5:B16) | C17: =SUM(C5:C16) | D17: =SUM(D5:D16) | E17: =SUM(E5:E16) | F17: =SUM(F5:F16)

Sheet Indicadores Financeiros
A1: Vida Plena S.A. — Indicadores Financeiros & Métricas de Performance
A2: Visão Sintética de Margens, Eficiência e Métricas Corporativas (2025)
A4: Indicador | B4: Fórmula / Critério | C4: Valor / Percentual
A5: Receita Total (Líquida) | B5: Soma da Receita Líquida no Ano | C5: ='DRE 2025'!B7
A6: Receita Média Mensal | B6: Média da Receita Líquida Mensal | C6: =AVERAGE('Comparativo Mensal'!B5:B16)
A7: Crescimento Anual | B7: Variação em relação ao exercício anterior (2024) | C7: 0.1425
A8: Margem Bruta | B8: Lucro Bruto / Receita Líquida | C8: ='DRE 2025'!B9/'DRE 2025'!B7
A9: Margem Operacional | B9: Resultado Operacional / Receita Líquida | C9: ='DRE 2025'!B13/'DRE 2025'!B7
A10: Margem Líquida | B10: Lucro Líquido / Receita Líquida | C10: ='DRE 2025'!B15/'DRE 2025'!B7
A11: EBITDA | B11: Resultado Operacional + Depreciação/Amortização | C11: ='DRE 2025'!B13+1850000
A12: Ticket Médio por Cliente | B12: Receita Líquida / Base de Clientes Ativos (1.450) | C12: ='DRE 2025'!B7/1450
A13: Receita por Colaborador | B13: Receita Líquida / Colaboradores (350) | C13: ='DRE 2025'!B7/350
A14: Custo Operacional Médio Mensal | B14: Média dos Custos Operacionais Mensais | C14: =AVERAGE('Comparativo Mensal'!C5:C16)

Sheet Dashboard
A1: Vida Plena S.A. — Painel Executivo Financeiro
A2: Principais Métricas de Resultado e Indicadores Chave de Desempenho (2025)
A4: Receita Total (Líquida) | C4: Lucro Líquido | E4: Receita Média Mensal | G4: Crescimento do Ano
A5: ='DRE 2025'!B7 | C5: ='DRE 2025'!B15 | E5: ='Indicadores Financeiros'!C6 | G5: ='Indicadores Financeiros'!C7
A7: Melhor Mês (Faturamento) | C7: Pior Mês (Faturamento) | E7: Percentual de Custos | G7: Percentual de Despesas
A8: =INDEX('Comparativo Mensal'!A5:A16, MATCH(MAX('Comparativo Mensal'!B5:B16), 'Comparativo Mensal'!B5:B16, 0)) | C8: =INDEX('Comparativo Mensal'!A5:A16, MATCH(MIN('Comparativo Mensal'!B5:B16), 'Comparativo Mensal'!B5:B16, 0)) | E8: =-'DRE 2025'!B8/'DRE 2025'!B7 | G8: =-SUM('DRE 2025'!B10:B12)/'DRE 2025'!B7
A10: Resumo das Principais Contas DRE
A11: Conta DRE | B11: Valor Consolidado (R$) | C11: % S/ Receita Líquida
A12: Receita Bruta | B12: ='DRE 2025'!B5 | C12: =B12/$B$13
A13: Receita Líquida | B13: ='DRE 2025'!B7 | C13: =B13/$B$13
A14: Lucro Bruto | B14: ='DRE 2025'!B9 | C14: =B14/$B$13
A15: Resultado Operacional (EBIT) | B15: ='DRE 2025'!B13 | C15: =B15/$B$13
A16: EBITDA | B16: ='Indicadores Financeiros'!C11 | C16: =B16/$B$13
A17: Lucro Líquido | B17: ='DRE 2025'!B15 | C17: =B17/$B$13
